rul_datasets/__init__.py
rul_datasets/adaption.py
rul_datasets/baseline.py
rul_datasets/core.py
rul_datasets/py.typed
rul_datasets/reader/__init__.py
rul_datasets/reader/abstract.py
rul_datasets/reader/cmapss.py
rul_datasets/reader/data_root.py
rul_datasets/reader/dummy.py
rul_datasets/reader/femto.py
rul_datasets/reader/ncmapss.py
rul_datasets/reader/saving.py
rul_datasets/reader/scaling.py
rul_datasets/reader/truncating.py
rul_datasets/reader/xjtu_sy.py
rul_datasets/ssl.py
rul_datasets/utils.py
rul_datasets-0.17.1.dist-info/METADATA
rul_datasets-0.17.1.dist-info/WHEEL
rul_datasets-0.17.1.dist-info/RECORD
