Metadata-Version: 2.1
Name: rul_datasets
Version: 0.17.1
Summary: A collection of datasets for RUL estimation as Lightning Data Modules.
Home-page: https://krokotsch.eu/rul-datasets
License: MIT
Author: Krokotsch, Tilman
Author-email: tilman.krokotsch@tu-berlin.de
Requires-Python: >=3.8,<4.0
Classifier: License :: OSI Approved :: MIT License
Classifier: Programming Language :: Python :: 3
Classifier: Programming Language :: Python :: 3.8
Classifier: Programming Language :: Python :: 3.9
Classifier: Programming Language :: Python :: 3.10
Classifier: Programming Language :: Python :: 3.11
Classifier: Programming Language :: Python :: 3.12
Classifier: Topic :: Scientific/Engineering
Classifier: Topic :: Scientific/Engineering :: Artificial Intelligence
Requires-Dist: h5py (>=3.10.0,<4.0.0)
Requires-Dist: pytorch-lightning (>1.4.4)
Requires-Dist: scikit-learn (>=1.0.0,<2.0.0)
Requires-Dist: torch (>1.9.0)
Requires-Dist: tqdm (>=4.62.2,<5.0.0)
Project-URL: Repository, https://github.com/tilman151/rul-datasets
